LICENSE
MANIFEST.in
README.rst
pavement.py
requirements-dev.txt
requirements.txt
setup.py
tox.ini
docs/Makefile
docs/make.bat
docs/source/README
docs/source/conf.py
docs/source/index.rst
docs/source/news.rst
docs/source/_static/.gitkeep
docs/source/api/modules.rst
docs/source/api/piecash_utilities.report.rst
docs/source/api/piecash_utilities.report_example.rst
docs/source/api/piecash_utilities.rst
docs/source/doc/doc.rst
gnucash_utilities.egg-info/PKG-INFO
gnucash_utilities.egg-info/SOURCES.txt
gnucash_utilities.egg-info/dependency_links.txt
gnucash_utilities.egg-info/not-zip-safe
gnucash_utilities.egg-info/requires.txt
gnucash_utilities.egg-info/top_level.txt
piecash_utilities/__init__.py
piecash_utilities/config.py
piecash_utilities/metadata.py
piecash_utilities/gnucash_books/all_account_types.gnucash
piecash_utilities/gnucash_books/book_schtx.gnucash
piecash_utilities/gnucash_books/default_book.gnucash
piecash_utilities/gnucash_books/empty_book.gnucash
piecash_utilities/gnucash_books/simple_sample.gnucash
piecash_utilities/gnucash_books/test_book.gnucash
piecash_utilities/report/__init__.py
piecash_utilities/report/options.py
piecash_utilities/report/report.py
piecash_utilities/report_example/__init__.py
piecash_utilities/report_example/report_simplest.py
piecash_utilities/report_example/report_simplest_book.py
piecash_utilities/report_example/report_simplest_parameters.py
piecash_utilities/templates/__init__.py
piecash_utilities/templates/python_report_template.scm
piecash_utilities/templates/report_example.html
piecash_utilities/templates/report_example.py
piecash_utilities/templates/report_inputs.txt
scripts/__init__.py
scripts/csv_import_export.py
scripts/export_norme_A47.py
scripts/gc_report.py
scripts/gc_report_create.py
scripts/gc_test.py
tests/test_basic.py
tests/test_integration.py