Metadata-Version: 1.1
Name: gnucash-utilities
Version: 0.1.5
Summary: Set of python scripts to work with GnuCash books.
Home-page: https://github.com/sdementen/gnucash-utilities
Author: sdementen
Author-email: sdementen@gmail.com
License: MIT
Keywords: GnuCash,python,utilities,piecash,report
Platform: any
Classifier: Development Status :: 4 - Beta
Classifier: Environment :: Console
Classifier: Intended Audience :: Developers
Classifier: Intended Audience :: Financial and Insurance Industry
Classifier: License :: OSI Approved :: MIT License
Classifier: Natural Language :: English
Classifier: Operating System :: OS Independent
Classifier: Programming Language :: Python :: 3.5
Classifier: Topic :: Office/Business
Classifier: Topic :: Office/Business :: Financial
Classifier: Topic :: Office/Business :: Financial :: Accounting
Classifier: Topic :: Software Development :: Libraries :: Python Modules
